d4m/__init__.py
d4m/__main__.py
d4m/api.py
d4m/common.py
d4m/divamod.py
d4m/dma.py
d4m/gamebanana.py
d4m/global_config.py
d4m/gui.py
d4m/manage.py
d4m/tui.py
d4m/res/__init__.py
d4m/res/logo.svg
d4m/res/nopreview.png
d4m-0.3.3.dist-info/LICENSE
d4m-0.3.3.dist-info/METADATA
d4m-0.3.3.dist-info/WHEEL
d4m-0.3.3.dist-info/entry_points.txt
d4m-0.3.3.dist-info/top_level.txt
d4m-0.3.3.dist-info/RECORD
