Metadata-Version: 2.1
Name: d4m
Version: 0.3.3
Summary: Project Diva MegaMix+ Mod Manager
Author-email: Brod8362 <brod8362@gmail.com>
License: MIT License
Project-URL: Source Code, https://github.com/Brod8362/d4m
Project-URL: Issues, https://github.com/Brod8362/d4m/issues
Classifier: Programming Language :: Python :: 3
Classifier: License :: OSI Approved :: MIT License
Classifier: Operating System :: OS Independent
Requires-Python: >=3.9
License-File: LICENSE
Requires-Dist: vdf (>=3.4)
Requires-Dist: toml (>=0.10.2)
Requires-Dist: colorama (>=0.4.5)
Requires-Dist: requests (>=2.27.1)
Requires-Dist: simple-term-menu (>=1.5.0)
Requires-Dist: packaging (>=21.3)
Requires-Dist: PySide6 (>=6.2.4)
Requires-Dist: libarchive (>=0.4.7)
Requires-Dist: appdirs (>=1.4.4)
